optax_adan/__init__.py
optax_adan/transform.py
optax_adan/transform_test.py
optax_adan-0.1.4.dist-info/LICENSE
optax_adan-0.1.4.dist-info/METADATA
optax_adan-0.1.4.dist-info/WHEEL
optax_adan-0.1.4.dist-info/top_level.txt
optax_adan-0.1.4.dist-info/RECORD
