Metadata-Version: 2.1
Name: optax-adan
Version: 0.1.4
Summary: An implementation of adan optimization algorithm for optax.
Home-page: https://github.com/hr0nix/optax-adan
Author: Boris Yangel
Author-email: boris.jangel@gmail.com
License: Apache License 2.0
Classifier: Development Status :: 3 - Alpha
Classifier: Environment :: Console
Classifier: Intended Audience :: Science/Research
Classifier: Intended Audience :: Developers
Classifier: License :: OSI Approved :: Apache Software License
Classifier: Operating System :: OS Independent
Classifier: Programming Language :: Python :: 3
Classifier: Topic :: Scientific/Engineering :: Artificial Intelligence
Classifier: Topic :: Software Development :: Libraries :: Python Modules
License-File: LICENSE
Requires-Dist: optax
